ds_plotting/__init__.py
ds_plotting/altair_config.py
ds_plotting/cleanup.py
ds_plotting/config.py
ds_plotting/main.py
ds_plotting/parse.py
ds_plotting/plot.py
ds_plotting/py.typed
ds_plotting/read_crux_common.py
ds_plotting/utils/__init__.py
ds_plotting/utils/altairconfig.py
ds_plotting/utils/config.py
ds_plotting/utils/logger.py
ds_plotting-0.2.0.dist-info/METADATA
ds_plotting-0.2.0.dist-info/WHEEL
ds_plotting-0.2.0.dist-info/entry_points.txt
ds_plotting-0.2.0.dist-info/licenses/LICENSE
ds_plotting-0.2.0.dist-info/RECORD
