Metadata-Version: 2.4
Name: ds-plotting
Version: 0.2.0
Author-email: Thomas Camminady <0milieux_member@icloud.com>
License-File: LICENSE
Requires-Python: >=3.11
Requires-Dist: altair>=5.5.0
Requires-Dist: fire>=0.7.1
Requires-Dist: ipython>=9.5.0
Requires-Dist: polars>=1.33.1
Requires-Dist: pycrux>=0.2.0
Requires-Dist: rich>=14.1.0
